{
	"configurations" : 
	[
		{
			"directories" : 
			[
				{
					"build" : ".",
					"hasInstallRule" : true,
					"jsonFile" : "directory-.-5b5209d69b31b9ba25b8.json",
					"minimumCMakeVersion" : 
					{
						"string" : "3.12"
					},
					"projectIndex" : 0,
					"source" : ".",
					"targetIndexes" : 
					[
						0,
						1,
						2,
						3
					]
				}
			],
			"name" : "",
			"projects" : 
			[
				{
					"directoryIndexes" : 
					[
						0
					],
					"name" : "pmb2_description",
					"targetIndexes" : 
					[
						0,
						1,
						2,
						3
					]
				}
			],
			"targets" : 
			[
				{
					"directoryIndex" : 0,
					"id" : "ament_cmake_python_build_pmb2_description_egg::@6890427a1f51a3e7e1df",
					"jsonFile" : "target-ament_cmake_python_build_pmb2_description_egg-9bb1376abe5ac8ba62bd.json",
					"name" : "ament_cmake_python_build_pmb2_description_egg",
					"projectIndex" : 0
				},
				{
					"directoryIndex" : 0,
					"id" : "ament_cmake_python_symlink_pmb2_description::@6890427a1f51a3e7e1df",
					"jsonFile" : "target-ament_cmake_python_symlink_pmb2_description-470baa6c5cbfe28e7175.json",
					"name" : "ament_cmake_python_symlink_pmb2_description",
					"projectIndex" : 0
				},
				{
					"directoryIndex" : 0,
					"id" : "pmb2_description_uninstall::@6890427a1f51a3e7e1df",
					"jsonFile" : "target-pmb2_description_uninstall-cdaef11433f53cc3e632.json",
					"name" : "pmb2_description_uninstall",
					"projectIndex" : 0
				},
				{
					"directoryIndex" : 0,
					"id" : "uninstall::@6890427a1f51a3e7e1df",
					"jsonFile" : "target-uninstall-8d6137727a9af6ad5d76.json",
					"name" : "uninstall",
					"projectIndex" : 0
				}
			]
		}
	],
	"kind" : "codemodel",
	"paths" : 
	{
		"build" : "/home/claudio/tiago_public_ws/build/pmb2_description",
		"source" : "/home/claudio/tiago_public_ws/src/pmb2_robot/pmb2_description"
	},
	"version" : 
	{
		"major" : 2,
		"minor" : 3
	}
}
