{
	"configurations" : 
	[
		{
			"directories" : 
			[
				{
					"build" : ".",
					"hasInstallRule" : true,
					"jsonFile" : "directory-.-f9478eb9a5db9862f72d.json",
					"minimumCMakeVersion" : 
					{
						"string" : "3.12"
					},
					"projectIndex" : 0,
					"source" : ".",
					"targetIndexes" : 
					[
						0,
						1
					]
				}
			],
			"name" : "",
			"projects" : 
			[
				{
					"directoryIndexes" : 
					[
						0
					],
					"name" : "pmb2_controller_configuration",
					"targetIndexes" : 
					[
						0,
						1
					]
				}
			],
			"targets" : 
			[
				{
					"directoryIndex" : 0,
					"id" : "pmb2_controller_configuration_uninstall::@6890427a1f51a3e7e1df",
					"jsonFile" : "target-pmb2_controller_configuration_uninstall-7a1e7fe772322dbfc166.json",
					"name" : "pmb2_controller_configuration_uninstall",
					"projectIndex" : 0
				},
				{
					"directoryIndex" : 0,
					"id" : "uninstall::@6890427a1f51a3e7e1df",
					"jsonFile" : "target-uninstall-1adbc356a9d9b78ff04b.json",
					"name" : "uninstall",
					"projectIndex" : 0
				}
			]
		}
	],
	"kind" : "codemodel",
	"paths" : 
	{
		"build" : "/home/claudio/tiago_public_ws/build/pmb2_controller_configuration",
		"source" : "/home/claudio/tiago_public_ws/src/pmb2_robot/pmb2_controller_configuration"
	},
	"version" : 
	{
		"major" : 2,
		"minor" : 3
	}
}
